pytest_roast.py
pytest_roast-1.3.0.post0.dist-info/LICENSE
pytest_roast-1.3.0.post0.dist-info/METADATA
pytest_roast-1.3.0.post0.dist-info/WHEEL
pytest_roast-1.3.0.post0.dist-info/entry_points.txt
pytest_roast-1.3.0.post0.dist-info/top_level.txt
pytest_roast-1.3.0.post0.dist-info/RECORD
