Metadata-Version: 2.1
Name: pytest-roast
Version: 1.3.0.post0
Summary: pytest plugin for ROAST configuration override and fixtures
Home-page: https://github.com/Xilinx/pytest-roast
Author: Ching-Hwa Yu
Author-email: chinghwa@xilinx.com
License: MIT
Keywords: roast
Platform: UNKNOWN
Classifier: Development Status :: 5 - Production/Stable
Classifier: Operating System :: POSIX :: Linux
Classifier: Programming Language :: Python :: 3.6
Classifier: Programming Language :: Python :: 3.7
Classifier: Programming Language :: Python :: 3.8
Classifier: Programming Language :: Python :: 3.9
Classifier: License :: OSI Approved :: MIT License
Requires-Python: >=3.6, <4
License-File: LICENSE
Requires-Dist: pytest
Requires-Dist: roast (>=2.0.0)
Provides-Extra: dev
Requires-Dist: pytest-mock ; extra == 'dev'
Requires-Dist: pytest-black ; extra == 'dev'
Requires-Dist: coverage ; extra == 'dev'
